odoo/addons/stock_quant_reservation_info/README.rst
odoo/addons/stock_quant_reservation_info/__init__.py
odoo/addons/stock_quant_reservation_info/__manifest__.py
odoo/addons/stock_quant_reservation_info/i18n/stock_quant_reservation_info.pot
odoo/addons/stock_quant_reservation_info/models/__init__.py
odoo/addons/stock_quant_reservation_info/models/stock_move_line.py
odoo/addons/stock_quant_reservation_info/models/stock_quant.py
odoo/addons/stock_quant_reservation_info/readme/CONTRIBUTORS.rst
odoo/addons/stock_quant_reservation_info/readme/DESCRIPTION.rst
odoo/addons/stock_quant_reservation_info/readme/USAGE.rst
odoo/addons/stock_quant_reservation_info/static/description/icon.png
odoo/addons/stock_quant_reservation_info/static/description/index.html
odoo/addons/stock_quant_reservation_info/tests/__init__.py
odoo/addons/stock_quant_reservation_info/tests/test_stock_quant_reservation_info.py
odoo/addons/stock_quant_reservation_info/views/stock_move_line.xml
odoo/addons/stock_quant_reservation_info/views/stock_quant.xml
odoo13_addon_stock_quant_reservation_info-13.0.1.0.1.dev3.dist-info/METADATA
odoo13_addon_stock_quant_reservation_info-13.0.1.0.1.dev3.dist-info/WHEEL
odoo13_addon_stock_quant_reservation_info-13.0.1.0.1.dev3.dist-info/top_level.txt
odoo13_addon_stock_quant_reservation_info-13.0.1.0.1.dev3.dist-info/RECORD
